{
    "formMeta": {
        "title": "2026年2月健康講座報名表",
        "version": "1.0",
        "liffId": "2008806287-9a1hHluF",
        "lineOaId": "@246trduk",
        "gasUrl": "https://script.google.com/macros/s/AKfycbx74tnCe5wk-9WXWR-6Nrb8VE1R3iaXq33T6tpitgjk0PCYreNSoilkQ6QSDhghf4jlPQ/exec"
    },
    "banner": {
        "enabled": true,
        "imageUrl": "https://i.duk.tw/xIs9FV.png",
        "altText": "健康講座橫幅"
    },
    "infoBlocks": [
        {
            "id": "activity-info",
            "enabled": true,
            "title": "活動內容",
            "content": "專業營養師分享健康飲食秘訣,教您如何透過飲食改善身體狀況。\n\n現場還有免費健康諮詢服務！\n\n名額有限,報名從速。"
        },
        {
            "id": "location",
            "enabled": true,
            "title": "地點",
            "placeName": "頭頸專研物理治療所",
            "address": "台北市信義虎林街164巷34號1樓",
            "showMap": true,
            "mapQuery": "頭頸專研物理治療所+台北市信義虎林街164巷34號1樓"
        }
    ],
    "formFields": [
        {
            "id": "session",
            "type": "radio",
            "enabled": true,
            "required": true,
            "title": "報名場次",
            "options": [
                "2/8 (六) 14:00 - 16:00",
                "2/15 (六) 14:00 - 16:00",
                "2/22 (六) 14:00 - 16:00"
            ]
        },
        {
            "id": "realName",
            "type": "text",
            "enabled": true,
            "required": true,
            "title": "姓名",
            "placeholder": "請輸入您的真實姓名"
        },
        {
            "id": "phone",
            "type": "text",
            "enabled": true,
            "required": true,
            "title": "聯絡電話",
            "placeholder": "請輸入手機號碼"
        },
        {
            "id": "gender",
            "type": "radio",
            "enabled": true,
            "required": true,
            "title": "性別",
            "layout": "horizontal",
            "options": [
                "男",
                "女"
            ]
        },
        {
            "id": "age",
            "type": "radio",
            "enabled": true,
            "required": true,
            "title": "年齡區段",
            "options": [
                "20歲以下",
                "21-35歲",
                "36-50歲",
                "51-65歲",
                "65歲以上"
            ]
        },
        {
            "id": "interests",
            "type": "checkbox",
            "enabled": true,
            "required": false,
            "title": "感興趣的主題 (可複選)",
            "options": [
                "營養諮詢",
                "運動指導",
                "心理健康",
                "慢性病管理"
            ]
        },
        {
            "id": "remind",
            "type": "remind-section",
            "enabled": true,
            "required": true,
            "title": "是否接收活動提醒",
            "methods": {
                "line": {
                    "enabled": true
                },
                "email": {
                    "enabled": true
                }
            }
        }
    ]
}